Metadata-Version: 2.1
Name: codemie-mcp-assistants
Version: 0.1.322
Summary: MCP server for connecting to CodeMie Assistants API
Author: Vadym Vlasenko
Author-email: vadym_vlasenko@epam.com
Requires-Python: >=3.12,<4.0
Classifier: Programming Language :: Python :: 3
Classifier: Programming Language :: Python :: 3.12
Requires-Dist: certifi (>=2025.1.31,<2026.0.0)
Requires-Dist: codemie-sdk-python (==0.1.322)
Requires-Dist: httpx (>=0.28.1,<0.29.0)
Requires-Dist: mcp (>=1.6.0,<2.0.0)
Requires-Dist: pydantic (>=2.11.2,<3.0.0)
